metrobus/__init__.py
metrobus/metrobus.py
metrobus-0.0.23.dist-info/METADATA
metrobus-0.0.23.dist-info/RECORD
metrobus-0.0.23.dist-info/WHEEL
metrobus-0.0.23.dist-info/top_level.txt
