Metadata-Version: 2.1
Name: metrobus
Version: 0.0.23
Summary: A package to allow flexible and quick programs on a message bus/kafka.
Home-page: https://github.com/chrisfauerbach/metrobus
Author: Chris Fauerbach
Author-email: chris@fauie.com
License: UNKNOWN
Platform: UNKNOWN
Classifier: Programming Language :: Python :: 3
Classifier: License :: OSI Approved :: MIT License
Classifier: Operating System :: OS Independent
